examples/README.md
examples/account_service_real_test.py
examples/analysis_service_real_test.py
examples/indicators_advanced_real_test.py
examples/indicators_real_test.py
examples/market_data_service_real_test.py
examples/reports_service_real_test.py
examples/trading_service_real_test.py
fubon_api_mcp_server/__init__.py
fubon_api_mcp_server/_version.py
fubon_api_mcp_server/account_service.py
fubon_api_mcp_server/analysis_service.py
fubon_api_mcp_server/config.py
fubon_api_mcp_server/enums.py
fubon_api_mcp_server/indicators.py
fubon_api_mcp_server/indicators_advanced.py
fubon_api_mcp_server/market_data_service.py
fubon_api_mcp_server/reports_service.py
fubon_api_mcp_server/server.py
fubon_api_mcp_server/trading_service.py
fubon_api_mcp_server/utils.py
fubon_api_mcp_server-2.2.4.dist-info/licenses/LICENSE
scripts/README.md
scripts/generate_release_notes.ps1
scripts/quick_check.ps1
scripts/release.ps1
scripts/update_version.ps1
scripts/version_config.json
tests/conftest.py
tests/test_account_service.py
tests/test_analysis_service.py
tests/test_config.py
tests/test_enums.py
tests/test_indicators.py
tests/test_indicators_advanced.py
tests/test_market_data_service.py
tests/test_market_data_service_extended.py
tests/test_market_data_service_sqlite.py
tests/test_reports_service.py
tests/test_trading_service.py
tests/test_trading_service_extended.py
tests/test_trading_service_price_type.py
tests/test_utils.py
vscode-extension/.vscodeignore
vscode-extension/CHANGELOG.md
vscode-extension/ICON_README.md
vscode-extension/LICENSE
vscode-extension/MCP_SETUP_GUIDE.md
vscode-extension/README.md
vscode-extension/WORKSPACE_FIX.md
vscode-extension/icon.png
vscode-extension/package.json
vscode-extension/images/support-qrcode.png
vscode-extension/src/extension.js
fubon_api_mcp_server-2.2.4.dist-info/METADATA
fubon_api_mcp_server-2.2.4.dist-info/WHEEL
fubon_api_mcp_server-2.2.4.dist-info/entry_points.txt
fubon_api_mcp_server-2.2.4.dist-info/top_level.txt
fubon_api_mcp_server-2.2.4.dist-info/RECORD
