Metadata-Version: 2.4
Name: fubon-api-mcp-server
Version: 2.2.4
Summary: 富邦證券 MCP 服務器 - Model Context Protocol 服務器用於富邦證券 API，提供完整的台股交易功能與市場數據查詢
Author-email: Jimmy Cui <mcp@fubon.com>
Maintainer-email: "Mofesto.Cui" <mofesto.cui@gmail.com>
License-Expression: Apache-2.0
Project-URL: Homepage, https://github.com/mofesto/fubon-api-mcp-server
Project-URL: Documentation, https://fubon-api-mcp-server.readthedocs.io/
Project-URL: Repository, https://github.com/mofesto/fubon-api-mcp-server
Project-URL: Issues, https://github.com/mofesto/fubon-api-mcp-server/issues
Project-URL: Changelog, https://github.com/mofesto/fubon-api-mcp-server/blob/main/CHANGELOG.md
Project-URL: PyPI, https://pypi.org/project/fubon-api-mcp-server/
Project-URL: Source, https://github.com/mofesto/fubon-api-mcp-server
Project-URL: Tracker, https://github.com/mofesto/fubon-api-mcp-server/issues
Keywords: fubon,securities,trading,mcp,model-context-protocol,taiwan-stock,api
Classifier: Development Status :: 4 - Beta
Classifier: Intended Audience :: Developers
Classifier: Intended Audience :: Financial and Insurance Industry
Classifier: Operating System :: OS Independent
Classifier: Programming Language :: Python :: 3
Classifier: Programming Language :: Python :: 3.10
Classifier: Programming Language :: Python :: 3.11
Classifier: Programming Language :: Python :: 3.12
Classifier: Programming Language :: Python :: 3.13
Classifier: Topic :: Office/Business :: Financial :: Investment
Classifier: Topic :: Software Development :: Libraries :: Python Modules
Classifier: Topic :: Internet :: WWW/HTTP :: Dynamic Content
Requires-Python: >=3.10
License-File: LICENSE
Requires-Dist: pandas
Requires-Dist: scipy
Requires-Dist: TA-Lib
Requires-Dist: fastmcp>=0.1.0
Requires-Dist: mcp>=1.0.0
Requires-Dist: pydantic>=2.0.0
Requires-Dist: python-dotenv>=1.0.0
Provides-Extra: dev
Requires-Dist: pytest>=7.0.0; extra == "dev"
Requires-Dist: pytest-cov>=4.0.0; extra == "dev"
Requires-Dist: pytest-xdist>=3.0.0; extra == "dev"
Requires-Dist: pytest-mock>=3.10.0; extra == "dev"
Requires-Dist: black>=23.0.0; extra == "dev"
Requires-Dist: isort>=5.12.0; extra == "dev"
Requires-Dist: flake8>=6.0.0; extra == "dev"
Requires-Dist: mypy>=1.0.0; extra == "dev"
Requires-Dist: pandas-stubs>=2.0.0; extra == "dev"
Requires-Dist: ruff>=0.25.0; extra == "dev"
Requires-Dist: bandit>=1.7.0; extra == "dev"
Requires-Dist: safety>=2.3.0; extra == "dev"
Requires-Dist: bump2version>=1.0.0; extra == "dev"
Requires-Dist: twine>=4.0.0; extra == "dev"
Requires-Dist: build>=1.0.0; extra == "dev"
Provides-Extra: docs
Requires-Dist: sphinx>=5.0.0; extra == "docs"
Requires-Dist: sphinx-rtd-theme>=1.2.0; extra == "docs"
Requires-Dist: myst-parser>=0.18.0; extra == "docs"
Dynamic: license-file
